{
  "last_update": "2026-01-11T06:35:07.892245+02:00",
  "signals": [
    {
      "asset": "GBPJPY_otc",
      "direction": "DOWN",
      "confidence": 0.78,
      "entry_time": "06:35",
      "duration": 4,
      "reason": "Тренд зазначений як DOWN, волатильність середня (0.2099%), ціна трохи вище короткострокових SMA, а останні свічки показують слабке пониження, тому очікуємо подальший рух вниз протягом 3‑4 хвилин.",
      "timestamp": "2026-01-11 06:34:58",
      "generated_at": "2026-01-11T06:34:59.794363+02:00",
      "volatility": 0.2099,
      "id": "GBPJPY_otc_20260111063459",
      "entry_delay": 1,
      "generated_at_utc": "2026-01-11T04:34:59.794414Z",
      "expires_at": "2026-01-11T06:44:59.794363+02:00"
    },
    {
      "asset": "EURUSD_otc",
      "direction": "DOWN",
      "confidence": 0.78,
      "entry_time": "06:37",
      "duration": 5,
      "reason": "Тренд явно вниз, ціна 1.12917 нижче SMA5 (1.12935) і SMA10 (1.12961). Волатильність низька (0.1257%), тому обираємо тривалість 5 хвилин. Останні свічки підтверджують слабкість, більшість закриттів нижче середніх.",
      "timestamp": "2026-01-11 06:35:02",
      "generated_at": "2026-01-11T06:35:02.774667+02:00",
      "volatility": 0.1257,
      "id": "EURUSD_otc_20260111063502",
      "entry_delay": 2,
      "generated_at_utc": "2026-01-11T04:35:02.774715Z",
      "expires_at": "2026-01-11T06:45:02.774667+02:00"
    },
    {
      "asset": "USDJPY_otc",
      "direction": "UP",
      "confidence": 0.85,
      "entry_time": "06:37",
      "duration": 5,
      "reason": "Тренд UP підтверджений SMA5 > SMA10 і поточною ціною вище обох середніх; низька волатильність (<0.2%) дозволяє тримати позицію 5 хвилин, очікується подальший підйом.",
      "timestamp": "2026-01-11 06:35:05",
      "generated_at": "2026-01-11T06:35:05.890883+02:00",
      "volatility": 0.0412,
      "id": "USDJPY_otc_20260111063505",
      "entry_delay": 2,
      "generated_at_utc": "2026-01-11T04:35:05.890930Z",
      "expires_at": "2026-01-11T06:45:05.890883+02:00"
    }
  ],
  "timezone": "Europe/Kiev (UTC+2)",
  "total_signals": 3,
  "active_signals": 3,
  "generation_count": 247
}