{
  "last_update": "2025-12-27T21:54:47.531299",
  "signals": [
    {
      "asset": "GBPJPY_otc",
      "direction": "DOWN",
      "confidence": 0.8,
      "entry_time": "20:58",
      "reason": "Від'ємний тренд останніх 10 свічок, рівень опору на 233.15, низький об'єм торгів",
      "timestamp": "2025-12-27 20:54:00",
      "generated_at": "2025-12-27T21:54:45.711731"
    },
    {
      "asset": "EURUSD_otc",
      "direction": "DOWN",
      "confidence": 0.8,
      "entry_time": "20:58",
      "reason": "Відповідно до аналізу останніх 10 свічок, загальний тренд вказує на зниження ціни. Рівень опору знаходиться біля 1.1708, а рівень підтримки - біля 1.1674. Ключові технічні індикатори, такі як лінії тренду та індикатор Relative Strength Index (RSI), вказують на перевищення ціни, що може призвести до коригування вниз. Волатильність останніх свічок також вказує на можливе зниження ціни.",
      "timestamp": "2025-12-27 20:56:00",
      "generated_at": "2025-12-27T21:54:46.750910"
    },
    {
      "asset": "USDJPY_otc",
      "direction": "UP",
      "confidence": 0.8,
      "entry_time": "20:58",
      "reason": "Загальний тренд показує зростання, рівень підтримки знаходиться біля 155.77, а рівень опору - біля 155.88. Ключові технічні індикатори, такі як RSI та MACD, вказують на можливість подальшого зростання. Волатильність відносно низька, що свідчить про можливість подальшого руху в одному напрямку.",
      "timestamp": "2025-12-27 20:56:00",
      "generated_at": "2025-12-27T21:54:47.531280"
    }
  ]
}