{
  "last_update": "2026-01-27T10:37:08.304711+02:00",
  "signals": [
    {
      "asset": "GBPJPY_otc",
      "direction": "DOWN",
      "confidence": 0.82,
      "entry_time": "10:38",
      "duration": 3,
      "reason": "RSI near neutral and trending down, MACD histogram negative, price below EMA9 and EMA21, Bollinger Bands show price slipping under the middle band, Stochastic falling below 80, clear downtrend with lower highs/lows and predominance of bearish candles",
      "timestamp": "2026-01-27 10:36:56",
      "generated_at": "2026-01-27T10:36:58.698874+02:00",
      "volatility": 0.2641,
      "id": "GBPJPY_otc_20260127103658",
      "entry_delay": 2,
      "generated_at_utc": "2026-01-27T08:36:58.698914Z",
      "expires_at": "2026-01-27T10:46:58.698874+02:00"
    },
    {
      "asset": "USDJPY_otc",
      "direction": "DOWN",
      "confidence": 0.82,
      "entry_time": "10:39",
      "duration": 3,
      "reason": "Низька волатильність (0.04%), останні 3 свічки показують пониження ціни, EMA 9 нижче EMA 21, MACD зменшується, RSI близько 45‑50 (нейтрально‑знижено), Stochastic ~50, Bollinger Bands в центрі. Усі індикатори вказують на слабкий, проте впевнений, короткостроковий медвежий рух.",
      "timestamp": "2026-01-27 10:37:05",
      "generated_at": "2026-01-27T10:37:06.303775+02:00",
      "volatility": 0.0426,
      "id": "USDJPY_otc_20260127103706",
      "entry_delay": 2,
      "generated_at_utc": "2026-01-27T08:37:06.303821Z",
      "expires_at": "2026-01-27T10:47:06.303775+02:00"
    }
  ],
  "timezone": "Europe/Kiev (UTC+2)",
  "total_signals": 2,
  "active_signals": 2,
  "generation_count": 643
}