{
  "last_update": "2026-01-22T13:57:36.231006+02:00",
  "signals": [
    {
      "asset": "GBPJPY_otc",
      "direction": "DOWN",
      "confidence": 0.78,
      "entry_time": "13:59",
      "duration": 3,
      "reason": "Recent 3‑minute down candles, EMA9 below EMA21, MACD histogram negative, RSI ~48 indicating neutral‑to‑bearish momentum, price touching upper Bollinger Band and bearish engulfing at 14:25 suggest short‑term downside",
      "timestamp": "2026-01-22 13:57:25",
      "generated_at": "2026-01-22T13:57:26.708967+02:00",
      "volatility": 0.2048,
      "id": "GBPJPY_otc_20260122135726",
      "entry_delay": 2,
      "generated_at_utc": "2026-01-22T11:57:26.709000Z",
      "expires_at": "2026-01-22T14:07:26.708967+02:00"
    },
    {
      "asset": "EURUSD_otc",
      "direction": "DOWN",
      "confidence": 0.81,
      "entry_time": "13:59",
      "duration": 3,
      "reason": "RSI≈48 (neutral), MACD slightly negative, EMA9 below EMA21 indicating downtrend, price near lower half of Bollinger Bands, Stochastic≈45, recent 1‑min candles show consecutive bearish closes with no strong reversal pattern",
      "timestamp": "2026-01-22 13:57:28",
      "generated_at": "2026-01-22T13:57:30.495519+02:00",
      "volatility": 0.1051,
      "id": "EURUSD_otc_20260122135730",
      "entry_delay": 2,
      "generated_at_utc": "2026-01-22T11:57:30.495565Z",
      "expires_at": "2026-01-22T14:07:30.495519+02:00"
    },
    {
      "asset": "USDJPY_otc",
      "direction": "UP",
      "confidence": 0.78,
      "entry_time": "13:59",
      "duration": 3,
      "reason": "Recent bullish candles, price above EMA9/21, RSI around 73 (overbought but still rising), MACD line above signal with expanding positive histogram, price near upper Bollinger Band but trend remains upward, Stochastic %K above %D in overbought zone, no clear reversal candlestick pattern yet.",
      "timestamp": "2026-01-22 13:57:32",
      "generated_at": "2026-01-22T13:57:34.229759+02:00",
      "volatility": 0.0887,
      "id": "USDJPY_otc_20260122135734",
      "entry_delay": 2,
      "generated_at_utc": "2026-01-22T11:57:34.229798Z",
      "expires_at": "2026-01-22T14:07:34.229759+02:00"
    }
  ],
  "timezone": "Europe/Kiev (UTC+2)",
  "total_signals": 3,
  "active_signals": 3,
  "generation_count": 475
}