{
  "last_update": "2026-01-10T19:50:06.500476+02:00",
  "signals": [
    {
      "asset": "GBPJPY_otc",
      "direction": "UP",
      "confidence": 0.78,
      "entry_time": "19:42",
      "duration": 5,
      "reason": "Ціна 224.23200 вище SMA5 (224.08460) і SMA10 (224.06870), тренд визначено як UP, волатильність низька (0.1482 %), тому очікуємо продовження зростання протягом 5 хвилин.",
      "timestamp": "2026-01-10 19:40:24",
      "generated_at": "2026-01-10T19:40:24.972478+02:00",
      "volatility": 0.1482,
      "id": "GBPJPY_otc_20260110194024",
      "entry_delay": 2,
      "generated_at_utc": "2026-01-10T17:40:24.972525Z",
      "expires_at": "2026-01-10T19:50:24.972478+02:00"
    },
    {
      "asset": "EURUSD_otc",
      "direction": "UP",
      "confidence": 0.82,
      "entry_time": "19:41",
      "duration": 4,
      "reason": "Ціна перебуває вище SMA 5 і SMA 10, тренд зростаючий, волатильність середня, останні свічки показують підвищення, тому очікуємо подальший рух вгору",
      "timestamp": "2026-01-10 19:40:27",
      "generated_at": "2026-01-10T19:40:28.462773+02:00",
      "volatility": 0.2498,
      "id": "EURUSD_otc_20260110194028",
      "entry_delay": 1,
      "generated_at_utc": "2026-01-10T17:40:28.462819Z",
      "expires_at": "2026-01-10T19:50:28.462773+02:00"
    },
    {
      "asset": "USDJPY_otc",
      "direction": "UP",
      "confidence": 0.78,
      "entry_time": "19:42",
      "duration": 5,
      "reason": "Тренд визначений як UP, ціна вище SMA10 і близька до SMA5, низька волатильність (0.0824%) вказує на стабільний рух, останні свічки показують переважаюче зростання.",
      "timestamp": "2026-01-10 19:40:30",
      "generated_at": "2026-01-10T19:40:32.085613+02:00",
      "volatility": 0.0824,
      "id": "USDJPY_otc_20260110194032",
      "entry_delay": 2,
      "generated_at_utc": "2026-01-10T17:40:32.085661Z",
      "expires_at": "2026-01-10T19:50:32.085613+02:00"
    },
    {
      "asset": "GBPJPY_otc",
      "direction": "UP",
      "confidence": 0.78,
      "entry_time": "19:51",
      "duration": 5,
      "reason": "Тренд визначений як UP, ціна перебуває вище SMA5 і SMA10, а волатильність низька (<0.2%), що дозволяє обрати тривалість 5 хвилин. Підтримка ціни на рівні 224.07‑224.11 підтверджує подальший рух вгору.",
      "timestamp": "2026-01-10 19:49:57",
      "generated_at": "2026-01-10T19:49:58.116428+02:00",
      "volatility": 0.1513,
      "id": "GBPJPY_otc_20260110194958",
      "entry_delay": 2,
      "generated_at_utc": "2026-01-10T17:49:58.116476Z",
      "expires_at": "2026-01-10T19:59:58.116428+02:00"
    },
    {
      "asset": "EURUSD_otc",
      "direction": "UP",
      "confidence": 0.78,
      "entry_time": "19:52",
      "duration": 5,
      "reason": "Тренд явно восходящий, ціна вище SMA5 і SMA10, останні свічки показують зростання максимумів і закриття вище відкриття, волатильність низька, тому обираємо тривалість 5 хвилин.",
      "timestamp": "2026-01-10 19:50:00",
      "generated_at": "2026-01-10T19:50:01.337918+02:00",
      "volatility": 0.173,
      "id": "EURUSD_otc_20260110195001",
      "entry_delay": 2,
      "generated_at_utc": "2026-01-10T17:50:01.337967Z",
      "expires_at": "2026-01-10T20:00:01.337918+02:00"
    },
    {
      "asset": "USDJPY_otc",
      "direction": "DOWN",
      "confidence": 0.78,
      "entry_time": "19:52",
      "duration": 5,
      "reason": "Ціна нижче SMA5 і SMA10, тренд DOWN, низька волатильність, очікуємо подальше падіння",
      "timestamp": "2026-01-10 19:50:03",
      "generated_at": "2026-01-10T19:50:04.499487+02:00",
      "volatility": 0.1096,
      "id": "USDJPY_otc_20260110195004",
      "entry_delay": 2,
      "generated_at_utc": "2026-01-10T17:50:04.499539Z",
      "expires_at": "2026-01-10T20:00:04.499487+02:00"
    }
  ],
  "timezone": "Europe/Kiev (UTC+2)",
  "total_signals": 6,
  "active_signals": 6,
  "generation_count": 223
}