{
  "last_update": "2026-01-13T01:56:15.065449+02:00",
  "signals": [
    {
      "asset": "GBPJPY_otc",
      "direction": "UP",
      "confidence": 0.82,
      "entry_time": "01:48",
      "duration": 3,
      "reason": "Price shows a slight upward bias on the 1‑minute chart. EMA9 is above EMA21, MACD histogram is positive, RSI is in the mid‑50s, Stochastic is below the overbought zone, and recent candles display more bullish than bearish bodies, indicating short‑term buying pressure.",
      "timestamp": "2026-01-13 01:46:33",
      "generated_at": "2026-01-13T01:46:35.085949+02:00",
      "volatility": 0.2847,
      "id": "GBPJPY_otc_20260113014635",
      "entry_delay": 2,
      "generated_at_utc": "2026-01-12T23:46:35.085981Z",
      "expires_at": "2026-01-13T01:56:35.085949+02:00"
    },
    {
      "asset": "EURUSD_otc",
      "direction": "UP",
      "confidence": 0.82,
      "entry_time": "01:48",
      "duration": 3,
      "reason": "RSI ~58 (neutral‑slightly bullish), MACD line crossed above signal, price trading above EMA9 and EMA21 indicating uptrend, Bollinger Bands show price near upper band but still rising, Stochastic %K≈80/%D≈75 (overbought yet momentum upward), recent bullish candles and a bullish engulfing pattern support short‑term upside",
      "timestamp": "2026-01-13 01:46:37",
      "generated_at": "2026-01-13T01:46:38.835428+02:00",
      "volatility": 0.1029,
      "id": "EURUSD_otc_20260113014638",
      "entry_delay": 2,
      "generated_at_utc": "2026-01-12T23:46:38.835470Z",
      "expires_at": "2026-01-13T01:56:38.835428+02:00"
    },
    {
      "asset": "USDJPY_otc",
      "direction": "UP",
      "confidence": 0.78,
      "entry_time": "01:48",
      "duration": 3,
      "reason": "EMA9 is above EMA21 and both are below the current price, indicating a short‑term uptrend. Price is trading near the middle‑upper Bollinger Band, RSI is around 58 (neutral‑bullish) and MACD histogram is positive. Stochastic is rising but not yet overbought, supporting momentum. The 02:13 candle is a strong bullish candle after a brief pull‑back, and the overall pattern shows higher highs than lows. Combined signals give >75% confidence for a short‑term rise.",
      "timestamp": "2026-01-13 01:46:41",
      "generated_at": "2026-01-13T01:46:42.867878+02:00",
      "volatility": 0.0908,
      "id": "USDJPY_otc_20260113014642",
      "entry_delay": 2,
      "generated_at_utc": "2026-01-12T23:46:42.867915Z",
      "expires_at": "2026-01-13T01:56:42.867878+02:00"
    },
    {
      "asset": "GBPJPY_otc",
      "direction": "DOWN",
      "confidence": 0.75,
      "entry_time": "01:58",
      "duration": 3,
      "reason": "Тренд вниз. Волатильність: 0.09%",
      "timestamp": "2026-01-13 01:56:03",
      "generated_at": "2026-01-13T01:56:05.709162+02:00",
      "volatility": 0.0928,
      "id": "GBPJPY_otc_20260113015605",
      "entry_delay": 2,
      "generated_at_utc": "2026-01-12T23:56:05.709193Z",
      "expires_at": "2026-01-13T02:06:05.709162+02:00"
    },
    {
      "asset": "EURUSD_otc",
      "direction": "UP",
      "confidence": 0.75,
      "entry_time": "01:58",
      "duration": 3,
      "reason": "Тренд вгору. Волатильність: 0.14%",
      "timestamp": "2026-01-13 01:56:08",
      "generated_at": "2026-01-13T01:56:09.877628+02:00",
      "volatility": 0.1398,
      "id": "EURUSD_otc_20260113015609",
      "entry_delay": 2,
      "generated_at_utc": "2026-01-12T23:56:09.877659Z",
      "expires_at": "2026-01-13T02:06:09.877628+02:00"
    },
    {
      "asset": "USDJPY_otc",
      "direction": "UP",
      "confidence": 0.78,
      "entry_time": "01:58",
      "duration": 3,
      "reason": "RSI is near 55 indicating mild bullish momentum, MACD line is slightly above signal, price is above EMA9 and EMA21, Bollinger Bands show price near the lower half of the band suggesting room to rise, Stochastic is climbing from oversold region, recent candles show a slight upward bias with more higher closes than lower. Trend on 1‑minute chart appears bullish.",
      "timestamp": "2026-01-13 01:56:12",
      "generated_at": "2026-01-13T01:56:13.064494+02:00",
      "volatility": 0.0768,
      "id": "USDJPY_otc_20260113015613",
      "entry_delay": 2,
      "generated_at_utc": "2026-01-12T23:56:13.064529Z",
      "expires_at": "2026-01-13T02:06:13.064494+02:00"
    }
  ],
  "timezone": "Europe/Kiev (UTC+2)",
  "total_signals": 6,
  "active_signals": 6,
  "generation_count": 360
}